README.rst
setup.py
tset/__init__.py
tset/tset.py
tset.egg-info/PKG-INFO
tset.egg-info/SOURCES.txt
tset.egg-info/dependency_links.txt
tset.egg-info/top_level.txt