Metadata-Version: 1.1
Name: tset
Version: 0.1.1
Summary: time sets for Python
Home-page: https://github.com/ajschumacher/tset
Author: Aaron Schumacher
Author-email: ajschumacher@gmail.com
License: MIT
Download-URL: https://github.com/ajschumacher/tset/tarball/0.1.1
Platform: UNKNOWN
